LICENSE
README.md
setup.py
multiurl/__init__.py
multiurl/base.py
multiurl/downloader.py
multiurl/file.py
multiurl/ftp.py
multiurl/heuristics.py
multiurl/http.py
multiurl/multipart.py
multiurl/multiurl.py
multiurl.egg-info/PKG-INFO
multiurl.egg-info/SOURCES.txt
multiurl.egg-info/dependency_links.txt
multiurl.egg-info/requires.txt
multiurl.egg-info/top_level.txt
multiurl.egg-info/zip-safe
tests/test_downloader.py
tests/test_file.py
tests/test_robust.py